json_urley/__init__.py
json_urley/_path_element.py
json_urley/json_urley_error.py
json_urley-1.0.3.dist-info/METADATA
json_urley-1.0.3.dist-info/WHEEL
json_urley-1.0.3.dist-info/top_level.txt
json_urley-1.0.3.dist-info/RECORD
