Metadata-Version: 2.1
Name: json-urley
Version: 1.0.3
Summary: A tight standard for converting json objects to and from URL parameters.
Home-page: https://github.com/tofarr/json-urley
Author: Tim O'Farrell
Author-email: tofarr@gmail.com
Classifier: Programming Language :: Python :: 3
Classifier: License :: OSI Approved :: MIT License
Classifier: Operating System :: OS Independent
Requires-Python: >=3.7
Provides-Extra: dev
Requires-Dist: black ~=23.3 ; extra == 'dev'
Requires-Dist: pytest ~=7.2 ; extra == 'dev'
Requires-Dist: pytest-cov ~=4.0 ; extra == 'dev'
Requires-Dist: pytest-xdist ~=3.2 ; extra == 'dev'
Requires-Dist: pylint ~=3.0 ; extra == 'dev'
